{
	"Greenland": [
		[35, 72, -17, 25],
		[50, 60, -100, -50],
		[33, 50, -100, -50]
	],
	"Antarctica": [
		[-56, -30, -76, -52],
		[-56, -30, 111, 179],
		[-56, -30, 7, 53]
	],
	"Africa": [
		[-8, 2, 32, 42],
		[-13, 7, 27, 47],
		[-18, 12, 22, 52]
	],
	"Asia": [
		[26, 36, 83.45, 93.45],
		[21, 41, 78.45, 98.45],
		[16, 46, 73.45, 103.45]
	],
	"Europe": [
		[41, 51, 2.9, 12.9],
		[36, 56, -2.1, 17.9],
		[31, 61, -7.1, 22.9]
	],
	"USA": [
		[40.75, 50.75, -120.35, -110.35],
		[35.75, 55.75, -125.35, -105.35],
		[30.75, 60.75, -130.35, -100.35]
	],
	"Alaska": [
		[59.9, 69.9, -146.65, -136.65],
		[54.9, 74.9, -151.65, -131.65],
		[49.9, 79.9, -156.65, -126.65]
	],
	"South America": [
		[-21.65, -11.65, -72.8, -62.8],
		[-26.65, -6.65, -77.8, -57.8],
		[-31.65, -1.65, -82.8, -52.8]
	]
}
